InvisibleCharm/Settings.py
InvisibleCharm/__init__.py
InvisibleCharm/__main__.py
InvisibleCharm/lib/Argparse.py
InvisibleCharm/lib/Console.py
InvisibleCharm/lib/File.py
InvisibleCharm/lib/__init__.py
InvisibleCharm/lib/data/Encryption.py
InvisibleCharm/lib/data/Prepare.py
InvisibleCharm/lib/data/__init__.py
InvisibleCharm/lib/operations/Embed.py
InvisibleCharm/lib/operations/Image.py
InvisibleCharm/lib/operations/Windows.py
InvisibleCharm/lib/operations/__init__.py
InvisibleCharm-2.0.4.dist-info/METADATA
InvisibleCharm-2.0.4.dist-info/WHEEL
InvisibleCharm-2.0.4.dist-info/entry_points.txt
InvisibleCharm-2.0.4.dist-info/top_level.txt
InvisibleCharm-2.0.4.dist-info/RECORD
