Metadata-Version: 2.1
Name: InvisibleCharm
Version: 2.0.4
Summary: InvisibleCharm is a python script that allows you to hide your files.
Home-page: https://github.com/MPCodeWriter21/InvisibleCharm
Author: CodeWriter21(Mehrad Pooryoussof)
Author-email: <CodeWriter21@gmail.com>
License: UNKNOWN
Keywords: python,python3,CodeWriter21,Hide,Hidden,InvisibleCharm,Invisible,Charm
Platform: UNKNOWN
Classifier: Programming Language :: Python :: 3
Classifier: Programming Language :: Python :: 3.7
Classifier: Operating System :: Unix
Classifier: Operating System :: MacOS :: MacOS X
Classifier: Operating System :: Microsoft :: Windows
Requires-Dist: log21
Requires-Dist: Pillow
Requires-Dist: pycryptodome
Requires-Dist: python-magic
